ai_git_utils/__init__.py
ai_git_utils/config_manager.py
ai_git_utils/git_operations.py
ai_git_utils/main.py
ai_git_utils/utils.py
ai_git_utils/cli/__init__.py
ai_git_utils/cli/app.py
ai_git_utils/cli/commit.py
ai_git_utils/cli/diff.py
ai_git_utils/cli/log.py
ai_git_utils/cli/model.py
ai_git_utils/cli/version.py
ai_git_utils/models/__init__.py
ai_git_utils/models/commit_message.py
ai_git_utils/models/config.py
ai_git_utils/services/__init__.py
ai_git_utils/services/ai_service.py
ai_git_utils/services/commit_service.py
ai_git_utils/services/prompt_builder.py
ai_git_utils-0.5.1.dist-info/METADATA
ai_git_utils-0.5.1.dist-info/WHEEL
ai_git_utils-0.5.1.dist-info/entry_points.txt
ai_git_utils-0.5.1.dist-info/licenses/LICENSE
ai_git_utils-0.5.1.dist-info/RECORD
