Metadata-Version: 2.3
Name: ai_git_utils
Version: 0.5.1
Summary: AI git utils is an intelligent Git commit assistant that leverages AI to enhance your Git workflow.
Project-URL: Homepage, https://github.com/twn39/aigit
Project-URL: Documentation, https://github.com/twn39/aigit
Project-URL: Repository, https://github.com/twn39/aigit
Project-URL: Source Code, https://github.com/twn39/aigit
Author-email: curry tang <twn39@163.com>
Maintainer-email: curry tang <twn39@163.com>
Keywords: ai,aigit,git
Classifier: Intended Audience :: Developers
Classifier: License :: OSI Approved :: MIT License
Classifier: Programming Language :: Python :: 3
Classifier: Programming Language :: Python :: 3.10
Classifier: Programming Language :: Python :: 3.11
Classifier: Programming Language :: Python :: 3.12
Classifier: Programming Language :: Python :: 3.13
Requires-Python: >=3.10
Requires-Dist: gitpython>=3.1.46
Requires-Dist: openai>=2.8.1
Requires-Dist: pip>=25.3
Requires-Dist: rich>=14.2.0
Requires-Dist: typer>=0.21.0
